setup.py
Flask_Pigeon.egg-info/PKG-INFO
Flask_Pigeon.egg-info/SOURCES.txt
Flask_Pigeon.egg-info/dependency_links.txt
Flask_Pigeon.egg-info/requires.txt
Flask_Pigeon.egg-info/top_level.txt
Flask_Pigeon.egg-info/zip-safe
flask_pigeon/__init__.py
flask_pigeon/constant.py
flask_pigeon/pigeon.py