Metadata-Version: 1.1
Name: Flask-Pigeon
Version: 0.11.0
Summary: Flask messages extension.
Home-page: http://github.com/reterVision/flask-pigeon
Author: reterVision
Author-email: reterclose@gmail.com
License: MIT
Platform: any
Classifier: Environment :: Web Environment
Classifier: Intended Audience :: Developers
Classifier: License :: OSI Approved :: MIT License
Classifier: Operating System :: OS Independent
Classifier: Programming Language :: Python
Classifier: Topic :: Internet :: WWW/HTTP :: Dynamic Content
Classifier: Topic :: Software Development :: Libraries :: Python Modules
